basic_find/__init__.py
basic_find/__main__.py
basic_find/basic_find.py
basic_find-0.0.3.dist-info/AUTHORS.rst
basic_find-0.0.3.dist-info/LICENSE
basic_find-0.0.3.dist-info/METADATA
basic_find-0.0.3.dist-info/WHEEL
basic_find-0.0.3.dist-info/top_level.txt
basic_find-0.0.3.dist-info/RECORD
