Metadata-Version: 2.1
Name: basic-find
Version: 0.0.3
Summary: Walk a file hierarchy
Home-page: https://github.com/arcseldon/basic_find
Author: Richard Seldon
Author-email: arcseldon@gmail.com
License: MIT license
Keywords: basic_find
Platform: UNKNOWN
Classifier: Development Status :: 2 - Pre-Alpha
Classifier: Intended Audience :: Developers
Classifier: License :: OSI Approved :: MIT License
Classifier: Natural Language :: English
Classifier: Programming Language :: Python :: 2
Classifier: Programming Language :: Python :: 2.7
Classifier: Programming Language :: Python :: 3
Classifier: Programming Language :: Python :: 3.4
Classifier: Programming Language :: Python :: 3.5
Classifier: Programming Language :: Python :: 3.6
Classifier: Programming Language :: Python :: 3.7
